{
  "build": {
    "markdownEngineName": "markdig",
    "content": [
      {
        "files": [
          "**/*.md",
          "**/*.yml"
        ],
        "exclude": [
          "**/obj/**",
          "**/includes/**",
          "_themes/**",
          "_themes.pdf/**",
          "**/docfx.json",
          "_repo.en-us/**",
          "README.md",
          "LICENSE",
          "LICENSE-CODE",
          "ThirdPartyNotices.md",
          "SECURITY.md"
        ]
      }
    ],
    "resource": [
      {
        "files": [
          "**/*.gif",
          "**/*.jpeg",
          "**/*.png",
          "**/*.jpg",
          "**/*.svg"
        ],
        "exclude": [
          "**/obj/**",
          "_themes/**",
          "_themes.pdf/**",
          "**/docfx.json",
          "_repo.en-us/**"
        ]
      }
    ],
    "overwrite": [],
    "externalReference": [],
    "globalMetadata": {
      "brand": "entra",
      "uhfHeaderId": "MSDocsHeader-Entra",
      "breadcrumb_path": "/entra/breadcrumb/toc.json",
      "extendBreadcrumb": false,
      "feedback_system": "Standard",
      "feedback_github_repo": "MicrosoftDocs/entra-docs",
      "feedback_product_url": "https://feedback.azure.com/d365community/forum/79b1327d-d925-ec11-b6e6-000d3a4f06a4",
      "searchScope": "Microsoft Entra",
      "author": "kenwith",
      "ms.author": "kenwith"
    },
    "fileMetadata": {
      "feedback_product_url": {
        "**/*.md": "https://feedback.azure.com/d365community/forum/79b1327d-d925-ec11-b6e6-000d3a4f06a4",
        "identity/**/*.md": "https://feedback.azure.com/d365community/forum/22920db1-ad25-ec11-b6e6-000d3a4f0789",
        "external-id/**/*.md": "https://aka.ms/microsoftentraexternalid",
        "identity-platform/*.md": "/entra/identity-platform/developer-support-help-options"
      },
      "learn_banner_products": {
        "docs/**/*.md": "entra",
        "docs/**/*.yml": "entra"
      },
      "featureFlags": {
        "docs/**/*.md": "show_learn_banner",
        "docs/**/*.yml": "show_learn_banner"
      },
      "author": {
        "external-id/**/*.md": "csmulligan",
        "external-id/**/*.yml": "csmulligan",
        "global-secure-access/**/*.md": "kenwith",
        "global-secure-access/**/*.yml": "kenwith",
        "id-governance/**/*.md": "owinfreyATL",
        "id-governance/**/*.yml": "owinfreyATL",
        "id-protection/**/*.md": "shlipsey3",
        "id-protection/**/*.yml": "shlipsey3",
        "identity/app-provisioning/**/*.md": "jenniferf-skc",
        "identity/app-provisioning/**/*.yml": "jenniferf-skc",
        "identity/app-proxy/**/*.md": "kenwith",
        "identity/app-proxy/**/*.yml": "kenwith",
        "identity/authentication/**/*.md": "justinha",
        "identity/authentication/**/*.yml": "justinha",
        "identity/conditional-access/**/*.md": "shlipsey3",
        "identity/conditional-access/**/*.yml": "shlipsey3",
        "verified-id/**/*.md": "barclayn",
        "verified-id/**/*.yml": "barclayn"
      },
      "ms.author": {
        "external-id/**/*.md": "cmulligan",
        "external-id/**/*.yml": "cmulligan",
        "global-secure-access/**/*.md": "kenwith",
        "global-secure-access/**/*.yml": "kenwith",
        "id-governance/**/*.md": "owinfrey",
        "id-governance/**/*.yml": "owinfrey",
        "id-protection/**/*.md": "sarahlipsey",
        "id-protection/**/*.yml": "sarahlipsey",
        "identity/app-provisioning/**/*.md": "jfields",
        "identity/app-provisioning/**/*.yml": "jfields",
        "identity/app-proxy/**/*.md": "kenwith",
        "identity/app-proxy/**/*.yml": "kenwith",
        "identity/authentication/**/*.md": "justinha",
        "identity/authentication/**/*.yml": "justinha",
        "identity/conditional-access/**/*.md": "sarahlipsey",
        "identity/conditional-access/**/*.yml": "sarahlipsey",
        "verified-id/**/*.md": "barclayn",
        "verified-id/**/*.yml": "barclayn"
      },
      "ms.service": {
        "external-id/**/*.md": "entra-external-id",
        "external-id/**/*.yml": "entra-external-id",
        "global-secure-access/**/*.md": "global-secure-access",
        "global-secure-access/**/*.yml": "global-secure-access",
        "id-governance/**/*.md": "entra-id-governance",
        "id-governance/**/*.yml": "entra-id-governance",
        "id-protection/**/*.md": "entra-id-protection",
        "id-protection/**/*.yml": "entra-id-protection",
        "identity/app-provisioning/**/*.md": "entra-id",
        "identity/app-provisioning/**/*.yml": "entra-id",
        "identity/app-proxy/**/*.md": "entra-id",
        "identity/app-proxy/**/*.yml": "entra-id",
        "identity/authentication/**/*.md": "entra-id",
        "identity/authentication/**/*.yml": "entra-id",
        "identity/conditional-access/**/*.md": "entra-id",
        "identity/conditional-access/**/*.yml": "entra-id",
        "verified-id/**/*.md": "entra-verified-id",
        "verified-id/**/*.yml": "entra-verified-id"
      },
      "ms.subservice": {
        "external-id/**/*.md": "external",
        "external-id/**/*.yml": "external",
        "identity/app-provisioning/**/*.md": "app-provisioning",
        "identity/app-provisioning/**/*.yml": "app-provisioning",
        "identity/app-proxy/**/*.md": "app-proxy",
        "identity/app-proxy/**/*.yml": "app-proxy",
        "identity/authentication/**/*.md": "authentication",
        "identity/authentication/**/*.yml": "authentication",
        "identity/conditional-access/**/*.md": "conditional-access",
        "identity/conditional-access/**/*.yml": "conditional-access"
      },
      "manager": {
        "agent-id/**/*.md": "pmwongera",
        "agent-id/**/*.yml": "pmwongera",
        "architecture/**/*.md": "dougeby",
        "architecture/**/*.yml": "dougeby",
        "external-id/**/*.md": "dougeby",
        "external-id/**/*.yml": "dougeby",
        "fundamentals/**/*.md": "dougeby",
        "fundamentals/**/*.yml": "dougeby",
        "global-secure-access/**/*.md": "dougeby",
        "global-secure-access/**/*.yml": "dougeby",
        "id-governance/**/*.md": "dougeby",
        "id-governance/**/*.yml": "dougeby",
        "id-protection/**/*.md": "dougeby",
        "id-protection/**/*.yml": "dougeby",
        "identity/**/*.md": "dougeby",
        "identity/**/*.yml": "dougeby",
        "identity/enterprise-apps/**/*.md": "dougeby",
        "identity/enterprise-apps/**/*.yml": "dougeby",
        "identity/saas-apps/**/*.md": "dougeby",
        "identity/saas-apps/**/*.yml": "dougeby",
        "permissions-management/**/*.md": "dougeby",
        "permissions-management/**/*.yml": "dougeby",
        "standards/**/*.md": "dougeby",
        "standards/**/*.yml": "dougeby",
        "verified-id/**/*.md": "dougeby",
        "verified-id/**/*.yml": "dougeby",
        "workload-id/**/*.md": "pmwongera",
        "workload-id/**/*.yml": "pmwongera"
      },
      "titleSuffix": {
        "*.md": "Microsoft Entra",
        "architecture/*.md": "Microsoft Entra",
        "architecture/*.yml": "Microsoft Entra",
        "external-id/*.md": "Microsoft Entra External ID",
        "external-id/*.yml": "Microsoft Entra External ID",
        "external-id/customers/*.md": "Microsoft Entra External ID",
        "external-id/customers/*.yml": "Microsoft Entra External ID",
        "fundamentals/*.md": "Microsoft Entra",
        "fundamentals/*.yml": "Microsoft Entra",
        "global-secure-access/*.md": "Global Secure Access",
        "global-secure-access/*.yml": "Global Secure Access",
        "id-governance/*.md": "Microsoft Entra ID Governance",
        "id-governance/*.yml": "Microsoft Entra ID Governance",
        "id-governance/privileged-identity-management/*.md": "Microsoft Entra ID Governance",
        "id-governance/privileged-identity-management/*.yml": "Microsoft Entra ID Governance",
        "id-protection/*.md": "Microsoft Entra ID Protection",
        "id-protection/*.yml": "Microsoft Entra ID Protection",
        "identity/**/*.md": "Microsoft Entra ID",
        "identity/**/*.yml": "Microsoft Entra ID",
        "identity/managed-identities-azure-resources/**/*.md": "Managed identities for Azure resources",
        "identity/managed-identities-azure-resources/**/*.yml": "Managed identities for Azure resources",
        "identity-platform/*.md": "Microsoft identity platform",
        "identity-platform/*.yml": "Microsoft identity platform",
        "permissions-management/*.md": "Microsoft Entra Permissions Management",
        "permissions-management/*.yml": "Microsoft Entra Permissions Management",
        "standards/*.md": "Microsoft Entra",
        "standards/*.yml": "Microsoft Entra",
        "verified-id/*.md": "Microsoft Entra Verified ID",
        "verified-id/*.yml": "Microsoft Entra Verified ID",
        "workload-id/*.md": "Microsoft Entra Workload ID",
        "workload-id/*.yml": "Microsoft Entra Workload ID"
      },
      "no-loc": {
        "includes/policy/**/*.md": "[audit, deny, modify, disabled, auditifnotexists, deployifnotexists]"
      }
    }, 
    "template": [
      "docs.html",
      "default",
      "DocFx.Plugins.PlantUml/template"
    ],
    "dest": "entra",
    "recommendations": true,
    "recommendation_types": ["Training", "Certification"],
    "contributors_to_exclude": [
      "alexbuckgit",
      "atookey",
      "chbain",
      "Court72",
      "deneha",
      "denrea",
      "DuncanmaMSFT",
      "garycentric",
      "GitHubber17",
      "hexiaokai",
      "itechedit",
      "Ja-Dunn",
      "Jak-MS",
      "JasonWHowell",
      "jborsecnik",
      "john-par",
      "jomolnar",
      "KatieCumming",
      "Kellylorenebaker",
      "kiwhit",
      "ktoliver",
      "Lisaco88",
      "MattGLaBelle",
      "meganbradley",
      "megvanhuygen",
      "openpublishingbuild",
      "PMEds28",
      "PRmerger",
      "PRMerger17",
      "PRMerger-2",
      "PRMerger3",
      "PRMerger4",
      "PRMerger5",
      "PRMerger9",
      "rjagiewich",
      "rmca14",
      "Saisang",
      "sdwheeler",
      "ShannonLeavitt",
      "ShawnJackson",
      "shawnmariejones",
      "TedA-M",
      "tfosmark",
      "TimShererWithAquent",
      "tiburd",
      "trishamc",
      "ttorble",
      "tysonn",
      "v-albemi",
      "v-andreaco",
      "v-anpasi",
      "v-ccolin",
      "v-dansch",
      "v-dihans",
      "v-rihow",
      "v-shils",
      "v-shmck",
      "v-thepet"
    ],
    "rules": {
      "sensitive-language-wl": {
        "exclude": [
          "identity/app-provisioning/sap-successfactors-integration-reference.md",
          "identity/authentication/howto-mfa-nps-extension-advanced.md"
        ]
      },
      "filename-incomplete": {
        "exclude": [
          "/identity/role-based-access-control/includes/*.md"
        ]
      }
    }
  } 
}
